[
    {
        "Total de T칤tulos": 2788,
        "N칰mero Chapeus": 8,
        "Chapeus": [
            "Blog da Julia Duailibi",
            "Bras칤lia",
            "7 de setembro",
            "Desfile em SP",
            "Cinema",
            "'Opera칞칚o Formosa'",
            "游꿚 Podcast",
            "Blog da Andr칠ia Sadi"
        ],
        "Total Not칤cias": 8,
        "Not칤cias": [
            "Brasil avisa que vai representar Argentina at칠 novo pa칤s ser escolhido ",
            "7 de Setembro: desfile tem representantes dos 3 Poderes, atletas ol칤mpicos e homenagem ao RS",
            "Em ato na Paulista, Bolsonaro pede anistia para condenados do 8/1 e chama Alexandre de Moraes de ditador",
            "PM cai do cavalo e morre antes de evento no samb칩dromo",
            "'The Room Next Door', de Almod칩var, leva o Le칚o de Ouro; veja todos vencedores",
            "Brasil faz exerc칤cio militar conjunto com tropas de China e EUA",
            "O ASSUNTO: como e quando a situa칞칚o de Silvio Almeida ficou insustent치vel",
            "Reuni칚o de Lula com Anielle teve s칩 mulheres como participantes"
        ],
        "Hora da not칤cia": [
            "H치 6 horas",
            "H치 8 horas",
            "H치 3 horas",
            "H치 3 horas",
            "H치 3 horas",
            "H치 3 horas",
            "H치 10 horas",
            "H치 11 horas",
            "H치 11 horas",
            "H치 11 horas",
            "H치 10 horas",
            "H치 10 horas",
            "H치 10 horas"
        ],
        "Em": [
            " Blog da Julia Duailibi ",
            " Pol칤tica ",
            " S칚o Paulo ",
            " S칚o Paulo ",
            " Cinema ",
            " Pol칤tica ",
            " Blog da Andr칠ia Sadi "
        ]
    }
]